snowflake/cortex/__init__.py
snowflake/cortex/_classify_text.py
snowflake/cortex/_complete.py
snowflake/cortex/_embed_text_1024.py
snowflake/cortex/_embed_text_768.py
snowflake/cortex/_extract_answer.py
snowflake/cortex/_finetune.py
snowflake/cortex/_sentiment.py
snowflake/cortex/_sse_client.py
snowflake/cortex/_summarize.py
snowflake/cortex/_translate.py
snowflake/cortex/_util.py
snowflake/ml/version.py
snowflake/ml/_internal/env.py
snowflake/ml/_internal/env_utils.py
snowflake/ml/_internal/file_utils.py
snowflake/ml/_internal/init_utils.py
snowflake/ml/_internal/migrator_utils.py
snowflake/ml/_internal/platform_capabilities.py
snowflake/ml/_internal/relax_version_strategy.py
snowflake/ml/_internal/telemetry.py
snowflake/ml/_internal/type_utils.py
snowflake/ml/_internal/exceptions/dataset_error_messages.py
snowflake/ml/_internal/exceptions/dataset_errors.py
snowflake/ml/_internal/exceptions/error_codes.py
snowflake/ml/_internal/exceptions/error_messages.py
snowflake/ml/_internal/exceptions/exceptions.py
snowflake/ml/_internal/exceptions/fileset_error_messages.py
snowflake/ml/_internal/exceptions/fileset_errors.py
snowflake/ml/_internal/exceptions/modeling_error_messages.py
snowflake/ml/_internal/exceptions/sql_error_codes.py
snowflake/ml/_internal/human_readable_id/adjectives.txt
snowflake/ml/_internal/human_readable_id/animals.txt
snowflake/ml/_internal/human_readable_id/hrid_generator.py
snowflake/ml/_internal/human_readable_id/hrid_generator_base.py
snowflake/ml/_internal/lineage/lineage_utils.py
snowflake/ml/_internal/utils/connection_params.py
snowflake/ml/_internal/utils/db_utils.py
snowflake/ml/_internal/utils/formatting.py
snowflake/ml/_internal/utils/identifier.py
snowflake/ml/_internal/utils/import_utils.py
snowflake/ml/_internal/utils/jwt_generator.py
snowflake/ml/_internal/utils/mixins.py
snowflake/ml/_internal/utils/parallelize.py
snowflake/ml/_internal/utils/pkg_version_utils.py
snowflake/ml/_internal/utils/query_result_checker.py
snowflake_ml_python-1.22.0.dist-info/licenses/LICENSE.txt
snowflake_ml_python-1.22.0.dist-info/METADATA
snowflake_ml_python-1.22.0.dist-info/WHEEL
snowflake_ml_python-1.22.0.dist-info/top_level.txt
snowflake_ml_python-1.22.0.dist-info/RECORD
