Metadata-Version: 2.4
Name: snowflake-ml-python
Version: 1.22.0
Summary: The machine learning client library that is used for interacting with Snowflake to build machine learning solutions.
Author-email: "Snowflake, Inc" <support@snowflake.com>
License: 
Project-URL: Homepage, https://github.com/snowflakedb/snowflake-ml-python
Project-URL: Documentation, https://docs.snowflake.com/developer-guide/snowpark-ml
Project-URL: Repository, https://github.com/snowflakedb/snowflake-ml-python
Project-URL: Issues, https://github.com/snowflakedb/snowflake-ml-python/issues
Project-URL: Changelog, https://github.com/snowflakedb/snowflake-ml-python/blob/master/CHANGELOG.md
Classifier: Development Status :: 5 - Production/Stable
Classifier: Environment :: Console
Classifier: Environment :: Other Environment
Classifier: Intended Audience :: Developers
Classifier: Intended Audience :: Education
Classifier: Intended Audience :: Information Technology
Classifier: Intended Audience :: System Administrators
Classifier: License :: OSI Approved :: Apache Software License
Classifier: Operating System :: OS Independent
Classifier: Programming Language :: Python :: 3.9
Classifier: Programming Language :: Python :: 3.10
Classifier: Programming Language :: Python :: 3.11
Classifier: Programming Language :: Python :: 3.12
Classifier: Topic :: Database
Classifier: Topic :: Software Development
Classifier: Topic :: Software Development :: Libraries
Classifier: Topic :: Software Development :: Libraries :: Application Frameworks
Classifier: Topic :: Software Development :: Libraries :: Python Modules
Classifier: Topic :: Scientific/Engineering :: Information Analysis
Requires-Python: <3.14,>=3.9
License-File: LICENSE.txt
Requires-Dist: anyio<5,>=3.5.0
Requires-Dist: cachetools<6,>=3.1.1
Requires-Dist: cloudpickle>=2.0.0
Requires-Dist: cryptography
Requires-Dist: fsspec[http]<2026,>=2024.6.1
Requires-Dist: importlib_resources<7,>=6.1.1
Requires-Dist: numpy<3,>=1.23
Requires-Dist: packaging<26,>=20.9
Requires-Dist: pandas<3,>=2.1.4
Requires-Dist: platformdirs<5
Requires-Dist: pyarrow<19.0.0
Requires-Dist: pydantic<3,>=2.8.2
Requires-Dist: pyjwt<3,>=2.0.0
Requires-Dist: pytimeparse<2,>=1.1.8
Requires-Dist: pyyaml<7,>=6.0
Requires-Dist: retrying<2,>=1.3.3
Requires-Dist: s3fs<2026,>=2024.6.1
Requires-Dist: scikit-learn<1.8
Requires-Dist: scipy<2,>=1.9
Requires-Dist: shap<1,>=0.46.0
Requires-Dist: snowflake-connector-python[pandas]<4,>=3.17.3
Requires-Dist: snowflake-snowpark-python!=1.26.0,<2,>=1.17.0
Requires-Dist: snowflake.core<2,>=1.0.2
Requires-Dist: sqlparse<1,>=0.4
Requires-Dist: tqdm<5
Requires-Dist: typing-extensions<5,>=4.1.0
Requires-Dist: xgboost<4
Provides-Extra: all
Requires-Dist: altair<6,>=5; extra == "all"
Requires-Dist: catboost<2,>=1.2.0; extra == "all"
Requires-Dist: keras<4,>=2.0.0; extra == "all"
Requires-Dist: lightgbm<5,>=4.1.0; extra == "all"
Requires-Dist: mlflow<3,>=2.16.0; extra == "all"
Requires-Dist: prophet<2,>=1.1.0; extra == "all"
Requires-Dist: sentence-transformers<4,>=2.7.0; extra == "all"
Requires-Dist: sentencepiece<0.2.0,>=0.1.95; extra == "all"
Requires-Dist: streamlit<2,>=1.30.0; extra == "all"
Requires-Dist: tensorflow<3,>=2.17.0; extra == "all"
Requires-Dist: tokenizers<1,>=0.15.1; extra == "all"
Requires-Dist: torch<3,>=2.0.1; extra == "all"
Requires-Dist: torchdata<1,>=0.4; extra == "all"
Requires-Dist: transformers!=4.51.3,<5,>=4.39.3; extra == "all"
Provides-Extra: altair
Requires-Dist: altair<6,>=5; extra == "altair"
Provides-Extra: catboost
Requires-Dist: catboost<2,>=1.2.0; extra == "catboost"
Provides-Extra: keras
Requires-Dist: keras<4,>=2.0.0; extra == "keras"
Requires-Dist: tensorflow<3,>=2.17.0; extra == "keras"
Requires-Dist: torch<3,>=2.0.1; extra == "keras"
Provides-Extra: lightgbm
Requires-Dist: lightgbm<5,>=4.1.0; extra == "lightgbm"
Provides-Extra: llm
Requires-Dist: mlflow<3,>=2.16.0; extra == "llm"
Requires-Dist: sentence-transformers<4,>=2.7.0; extra == "llm"
Requires-Dist: sentencepiece<0.2.0,>=0.1.95; extra == "llm"
Requires-Dist: tokenizers<1,>=0.15.1; extra == "llm"
Requires-Dist: torch<3,>=2.0.1; extra == "llm"
Requires-Dist: torchdata<1,>=0.4; extra == "llm"
Requires-Dist: transformers!=4.51.3,<5,>=4.39.3; extra == "llm"
Provides-Extra: mlflow
Requires-Dist: mlflow<3,>=2.16.0; extra == "mlflow"
Provides-Extra: prophet
Requires-Dist: prophet<2,>=1.1.0; extra == "prophet"
Provides-Extra: streamlit
Requires-Dist: streamlit<2,>=1.30.0; extra == "streamlit"
Provides-Extra: tensorflow
Requires-Dist: tensorflow<3,>=2.17.0; extra == "tensorflow"
Provides-Extra: torch
Requires-Dist: torch<3,>=2.0.1; extra == "torch"
Requires-Dist: torchdata<1,>=0.4; extra == "torch"
Provides-Extra: transformers
Requires-Dist: sentence-transformers<4,>=2.7.0; extra == "transformers"
Requires-Dist: sentencepiece<0.2.0,>=0.1.95; extra == "transformers"
Requires-Dist: tokenizers<1,>=0.15.1; extra == "transformers"
Requires-Dist: torch<3,>=2.0.1; extra == "transformers"
Requires-Dist: transformers!=4.51.3,<5,>=4.39.3; extra == "transformers"
Dynamic: license-file
